{
  "lang": "en",
  "id": "at-the-cross",
  "title": "At the Cross",
  "author": "Isaac Watts",
  "composer": "Ralph E. Hudson",
  "year": 1885,
  "categories": [
    "pentecostal",
    "salvation",
    "grace"
  ],
  "scriptureRefs": [
    {
      "ref": "Galatians 6:14",
      "note": "God forbid that I should glory, save in the cross of our Lord Jesus Christ"
    },
    {
      "ref": "Romans 5:8",
      "note": "While we were yet sinners, Christ died for us"
    }
  ],
  "story": "The verses of this hymn were originally written by Isaac Watts in 1707 as part of his hymn 'Alas! and Did My Saviour Bleed.' Nearly two centuries later, in 1885, Ralph E. Hudson added the beloved chorus 'At the cross, at the cross where I first saw the light' and set it to a new tune. Hudson's addition transformed the contemplative Watts poem into a joyful testimony of conversion that became a staple of revival meetings and Pentecostal worship services.",
  "lyrics": {
    "structure": [
      {
        "type": "verse",
        "number": 1,
        "lines": [
          "Alas! and did my Savior bleed,",
          "And did my Sov'reign die!",
          "Would He devote that sacred head",
          "For such a worm as I!"
        ]
      },
      {
        "type": "chorus",
        "lines": [
          "At the cross, at the cross where I first saw the light,",
          "And the burden of my heart rolled away,",
          "It was there by faith I received my sight,",
          "And now I am happy all the day!"
        ]
      },
      {
        "type": "verse",
        "number": 2,
        "lines": [
          "Was it for crimes that I had done",
          "He groaned upon the tree?",
          "Amazing pity! Grace unknown!",
          "And love beyond degree!"
        ]
      },
      {
        "type": "verse",
        "number": 3,
        "lines": [
          "Well might the sun in darkness hide,",
          "And shut his glories in,",
          "When Christ, the mighty Maker, died",
          "For man the creature's sin."
        ]
      },
      {
        "type": "verse",
        "number": 4,
        "lines": [
          "But drops of grief can ne'er repay",
          "The debt of love I owe;",
          "Here, Lord, I give myself away,",
          "'Tis all that I can do!"
        ]
      }
    ]
  },
  "translations": [],
  "publicDomain": true,
  "source": "Public Domain"
}