{
  "lang": "en",
  "id": "i-need-thee-every-hour",
  "title": "I Need Thee Every Hour",
  "author": "Annie S. Hawks",
  "composer": "Robert Lowry",
  "year": 1872,
  "categories": [
    "pentecostal",
    "devotion",
    "prayer"
  ],
  "scriptureRefs": [
    {
      "ref": "John 15:5",
      "note": "Without me ye can do nothing"
    },
    {
      "ref": "Psalm 46:1",
      "note": "God is our refuge and strength, a very present help in trouble"
    }
  ],
  "story": "Annie Sherwood Hawks wrote this hymn in June 1872 while going about her household duties in Brooklyn, New York. She later recalled that she was filled with a sense of nearness to her Master and wondered how anyone could live without Him in both joy and pain. She gave the poem to her pastor, Robert Lowry, who added the chorus and composed the tune. Hawks later said the full meaning of the hymn came to her only after her husband's death in 1888.",
  "lyrics": {
    "structure": [
      {
        "type": "verse",
        "number": 1,
        "lines": [
          "I need Thee every hour,",
          "Most gracious Lord;",
          "No tender voice like Thine",
          "Can peace afford."
        ]
      },
      {
        "type": "chorus",
        "lines": [
          "I need Thee, O I need Thee;",
          "Every hour I need Thee;",
          "O bless me now, my Savior,",
          "I come to Thee."
        ]
      },
      {
        "type": "verse",
        "number": 2,
        "lines": [
          "I need Thee every hour,",
          "Stay Thou nearby;",
          "Temptations lose their pow'r",
          "When Thou art nigh."
        ]
      },
      {
        "type": "verse",
        "number": 3,
        "lines": [
          "I need Thee every hour,",
          "In joy or pain;",
          "Come quickly and abide,",
          "Or life is vain."
        ]
      },
      {
        "type": "verse",
        "number": 4,
        "lines": [
          "I need Thee every hour;",
          "Teach me Thy will;",
          "And Thy rich promises",
          "In me fulfill."
        ]
      },
      {
        "type": "verse",
        "number": 5,
        "lines": [
          "I need Thee every hour,",
          "Most Holy One;",
          "O make me Thine indeed,",
          "Thou blessed Son."
        ]
      }
    ]
  },
  "translations": [],
  "publicDomain": true,
  "source": "Public Domain"
}